LICENSE
README.md
setup.py
batterydataextractor/__init__.py
batterydataextractor/config.py
batterydataextractor/errors.py
batterydataextractor/utils.py
batterydataextractor.egg-info/PKG-INFO
batterydataextractor.egg-info/SOURCES.txt
batterydataextractor.egg-info/dependency_links.txt
batterydataextractor.egg-info/not-zip-safe
batterydataextractor.egg-info/requires.txt
batterydataextractor.egg-info/top_level.txt
batterydataextractor/doc/__init__.py
batterydataextractor/doc/document.py
batterydataextractor/doc/element.py
batterydataextractor/doc/head.py
batterydataextractor/doc/meta.py
batterydataextractor/doc/text.py
batterydataextractor/model/__init__.py
batterydataextractor/model/base.py
batterydataextractor/model/model.py
batterydataextractor/nlp/__init__.py
batterydataextractor/nlp/abbrev.py
batterydataextractor/nlp/cem.py
batterydataextractor/nlp/lexicon.py
batterydataextractor/nlp/tag.py
batterydataextractor/nlp/tokenize.py
batterydataextractor/parse/__init__.py
batterydataextractor/parse/base.py
batterydataextractor/parse/bert.py
batterydataextractor/parse/cem.py
batterydataextractor/reader/__init__.py
batterydataextractor/reader/base.py
batterydataextractor/reader/elsevier.py
batterydataextractor/reader/markup.py
batterydataextractor/reader/plaintext.py
batterydataextractor/reader/rsc.py
batterydataextractor/reader/springer.py
batterydataextractor/scrape/__init__.py
batterydataextractor/scrape/base.py
batterydataextractor/scrape/clean.py
batterydataextractor/scrape/csstranslator.py
batterydataextractor/scrape/elsevier.py
batterydataextractor/scrape/rsc.py
batterydataextractor/scrape/springer.py
batterydataextractor/text/__init__.py
batterydataextractor/text/normalize.py
batterydataextractor/text/processors.py
tests/__init__.py
tests/test_doc_document.py
tests/test_doc_text.py
tests/test_nlp_abbrev.py
tests/test_nlp_cem.py
tests/test_nlp_sentence.py
tests/test_nlp_tag.py
tests/test_nlp_tokenize.py
tests/test_parse_bert.py
tests/test_parse_cem.py
tests/test_reader_clean.py
tests/test_reader_elsevier.py
tests/test_reader_markup.py
tests/test_reader_rsc.py
tests/test_reader_springer.py
tests/test_scrape.py
tests/test_text_normalize.py