Metadata-Version: 2.1
Name: batterydataextractor
Version: 0.0.6
Summary: BatteryDataExtractor: battery-aware text-mining software embedded with BERT models
Home-page: https://github.com/ShuHuang/batterydataextractor
Author: Shu Huang
Author-email: sh2009@cam.ac.uk
License: MIT License
Keywords: bde
Platform: UNKNOWN
Classifier: Intended Audience :: Developers
Classifier: Intended Audience :: Science/Research
Classifier: License :: OSI Approved :: MIT License
Classifier: Operating System :: OS Independent
Classifier: Programming Language :: Python :: 3
Classifier: Topic :: Internet :: WWW/HTTP :: Indexing/Search
Classifier: Topic :: Scientific/Engineering
Classifier: Topic :: Scientific/Engineering :: Artificial Intelligence
Classifier: Topic :: Scientific/Engineering :: Chemistry
License-File: LICENSE
